mplcursors.pth
mplcursors/__init__.py
mplcursors/_mplcursors.py
mplcursors/_pick_info.py
mplcursors-0.6.dist-info/LICENSE.txt
mplcursors-0.6.dist-info/METADATA
mplcursors-0.6.dist-info/WHEEL
mplcursors-0.6.dist-info/top_level.txt
mplcursors-0.6.dist-info/RECORD
