Metadata-Version: 2.1
Name: mplcursors
Version: 0.6
Summary: Interactive data selection cursors for Matplotlib.
Author: Antony Lee
License: zlib
Project-URL: Repository, https://github.com/anntzer/mplcursors
Classifier: Development Status :: 4 - Beta
Classifier: Framework :: Matplotlib
Classifier: License :: OSI Approved :: zlib/libpng License
Classifier: Programming Language :: Python :: 3
Requires-Python: >=3.7
License-File: LICENSE.txt
Requires-Dist: matplotlib!=3.7.1,>=3.1
Requires-Dist: importlib-metadata; python_version < "3.8"
Provides-Extra: docs
Requires-Dist: pandas; extra == "docs"
Requires-Dist: pydata_sphinx_theme!=0.10.1; extra == "docs"
Requires-Dist: sphinx; extra == "docs"
Requires-Dist: sphinx-gallery; extra == "docs"
